scenographer/__init__.py
scenographer/cli.py
scenographer/database.py
scenographer/relations.py
scenographer/sample.py
scenographer/scenographer.py
scenographer/utils.py
scenographer-0.1.1.dist-info/entry_points.txt
scenographer-0.1.1.dist-info/WHEEL
scenographer-0.1.1.dist-info/METADATA
scenographer-0.1.1.dist-info/RECORD
