Metadata-Version: 2.1
Name: scenographer
Version: 0.1.1
Summary: The cool dude who sets up the stage. Word.
Home-page: https://zyperco.github.io/scenographer/
Keywords: postgres,subset,sample
Author: Xavier Francisco
Author-email: xavier@zyper.com
Requires-Python: >=3.8,<4.0
Classifier: Programming Language :: Python :: 3
Classifier: Programming Language :: Python :: 3.8
Requires-Dist: commentjson (>=0.8.3,<0.9.0)
Requires-Dist: dict-digger (>=0.2.1,<0.3.0)
Requires-Dist: docopt (>=0.6.2,<0.7.0)
Requires-Dist: loguru (>=0.5.1,<0.6.0)
Requires-Dist: matplotlib (>=3.1.2,<4.0.0)
Requires-Dist: networkx (>=2.5,<3.0)
Requires-Dist: psycopg2-binary (>=2.8.5,<3.0.0)
Requires-Dist: pyrsistent (>=0.16.0,<0.17.0)
Requires-Dist: sqlalchemy (>=1.3.19,<2.0.0)
Requires-Dist: sqlalchemy-postgres-copy (>=0.5.0,<0.6.0)
Requires-Dist: sqlalchemy_utils (>=0.36.8,<0.37.0)
Project-URL: Documentation, https://zyperco.github.io/scenographer/
Project-URL: Repository, https://github.com/zyperco/scenographer/
